<?xml version="1.0" encoding="utf-8"?>
<odoo>
  <data>
     <!--  Formulario de origenes de obra     -->
        <record id="generales_origenes_obra_form_view" model="ir.ui.view">
            <field name="name">Generales Origenes_obra Form</field>
            <field name="model">generales.origenes_obra</field>
            <field name="arch" type="xml">
                <form string="origenes_obra form">
                    <sheet>
                        <group>
                            <field name="name"/>
                            <field name="observaciones"/>
                        </group>
                    </sheet>
                </form>
            </field>
        </record>

         <!--  vista tree      -->
        <record id="generales_origenes_obra_tree_view" model="ir.ui.view">
            <field name="name">Generales Origenes_obra Tree</field>
            <field name="model">generales.origenes_obra</field>
            <field name="arch" type="xml">
                <tree string="Origenes_obra tree">
                    <field name="name"/>
                    <field name="observaciones"/>
                </tree>
            </field>
        </record>

        <!--  action view      -->
        <record id="action_generales_origenes_obra" model="ir.actions.act_window">
            <field name="name">Orígenes de Obra</field>
            <field name="type">ir.actions.act_window</field>
            <field name="res_model">generales.origenes_obra</field>
            <field name="view_mode">tree,form</field>
            <field name="help" type="html">
              <p class="oe_view_nocontent_create">
                Crear nuevos orígenes de obra
              </p>
            </field>
        </record>
        <!-- crear menus       -->
        <menuitem id="generales_root" name="Información Básica" sequence="0"/>
        <menuitem id="generales" name="Generales" sequence="1" parent="generales_root"/>

        <menuitem id="firmas_logos" name="Firmas/logos" sequence="2" parent="generales_root"/>

        <menuitem id="generales_origenes_obra" parent="generales" name="Origenes de obra"
                  action="action_generales_origenes_obra" sequence="1"/>
  </data>
</odoo>